MANIFEST.in
README.md
setup.py
anthill/discovery/__init__.py
anthill/discovery/admin.py
anthill/discovery/handler.py
anthill/discovery/options.py
anthill/discovery/server.py
anthill/discovery/model/__init__.py
anthill/discovery/model/discovery.py
anthill_discovery.egg-info/PKG-INFO
anthill_discovery.egg-info/SOURCES.txt
anthill_discovery.egg-info/dependency_links.txt
anthill_discovery.egg-info/namespace_packages.txt
anthill_discovery.egg-info/not-zip-safe
anthill_discovery.egg-info/requires.txt
anthill_discovery.egg-info/top_level.txt