Metadata-Version: 1.0
Name: anthill-discovery
Version: 0.2
Summary: A dynamic server discovery service for Anthill platform
Home-page: https://github.com/anthill-platform/anthill-discovery
Author: desertkun
Author-email: desertkun@gmail.com
License: MIT
Platform: UNKNOWN
